{
  "@context": {
    "@import": "https://schema.org/",
    "schema": "https://schema.org/"
  },
  "@id": "https://w3id.org/marco-bolo/mbo_propval_eov_14",
  "@type": "PropertyValue",
  "description": "Essential Ocean Variable (EOV), Subsurface temperature, as defined by the Global Ocean Observing System. EOVs are a minimum set of key variables identified by the Global Ocean Observing System (GOOS) community that are critical to understanding ocean change and guiding policy.",
  "name": "Subsurface temperature",
  "propertyID": {
    "@id": "https://goosocean.org/document/17467"
  }
}
