{
    "@context": "http://www.w3.org/ns/csvw",
    "columns": [
        {
            "name": "personOrOrganisationId",
            "required": true,
            "titles": {
                "en": ["Person Or Organisation PID"]
            },
            "suppressOutput": true
        },        
        {
            "virtual": true,
            "propertyUrl": "rdf:type",
            "valueUrl": "https://schema.org/Person"
        }
    ],
    "aboutUrl": "{+personOrOrganisationId}",
    "primaryKey": [
        "personOrOrganisationId"
    ]
}